{"about.md":"COtCBgZp","docs_benchmarking.md":"Bea4qGtC","docs_builder.md":"vj95bpxc","docs_cli.md":"P6dyDugs","docs_codeanalysis.md":"BVDQMljd","docs_configuration.md":"D4Yr96ja","docs_essupport.md":"DZk4PWgM","docs_extensibility_customservermiddleware.md":"Cc8SvRTZ","docs_extensibility_customtasks.md":"BWSQGxIb","docs_extensibility_projectshims.md":"CtfiXVLs","docs_faq.md":"CMDx5n3W","docs_filesystem.md":"U89hlZr2","docs_gettingstarted.md":"CPgJ8l4R","docs_index.md":"CBcf5G6_","docs_openui5.md":"FOUYK7Z_","docs_overview.md":"DexgKed2","docs_privacy.md":"BsuLsbZL","docs_project.md":"B8Q0YUO6","docs_readme.md":"CCTsLCXO","docs_sapui5.md":"DOkKUOf5","docs_server.md":"CMJZ8WTi","docs_troubleshooting.md":"WklYROze","docs_updates_migrate-v1.md":"BFgP-HtM","docs_updates_migrate-v2.md":"CSW3qFa9","docs_updates_migrate-v3.md":"CmrmvvO8","docs_updates_migrate-v4.md":"8rJ-X2UU","docs_workspace.md":"C-iLic3x","guide_badgen.md":"B06F-5Sc","guide_getting-started.md":"Cv7PV3_B","guide_guidelines.md":"DgF625FI","guide_index.md":"BclhPIsV","guide_md-implicit-figures.md":"C-pDip4b","guide_md-languages.md":"C9peOsRQ","guide_md-plantuml.md":"CGoIwdQW","guide_tailwindcss.md":"JPUUpa5x","guide_trip-pin-ssr.md":"BUxOiKjw","guide_trip-pin.md":"CGOubNXo","guide_ui5wc.md":"BMif9xIp","guide_vue.md":"Cpb6G0VK","guide_zoomvanilla.md":"Qn3cp4Ir","index.md":"Dr6HQM98"}
